gwdtest/__init__.py
gwdtest/add_num.py
gwdtest-0.1.dist-info/METADATA
gwdtest-0.1.dist-info/WHEEL
gwdtest-0.1.dist-info/top_level.txt
gwdtest-0.1.dist-info/RECORD
