Metadata-Version: 2.1
Name: gwdtest
Version: 0.1
Summary: Test package for gwd
Author: GWD
License: UNKNOWN
Platform: UNKNOWN
